[
    {
        "OverviewPage": "",
        "Champion": "Smolder",
        "TournamentLevel": "Secondary",
        "GameCount": "1",
        "Link": "BaLiDo"
    },
    {
        "OverviewPage": "",
        "Champion": "Smolder",
        "TournamentLevel": "Secondary",
        "GameCount": "1",
        "Link": "carium"
    },
    {
        "OverviewPage": "",
        "Champion": "Smolder",
        "TournamentLevel": "Secondary",
        "GameCount": "1",
        "Link": "Pedro (Italian Player)"
    },
    {
        "OverviewPage": "",
        "Champion": "Smolder",
        "TournamentLevel": "Secondary",
        "GameCount": "1",
        "Link": "Pjames"
    },
    {
        "OverviewPage": "",
        "Champion": "Smolder",
        "TournamentLevel": "Secondary",
        "GameCount": "1",
        "Link": "Silva (North American Player)"
    },
    {
        "OverviewPage": "",
        "Champion": "Smolder",
        "TournamentLevel": "Secondary",
        "GameCount": "2",
        "Link": "MZE"
    },
    {
        "OverviewPage": "",
        "Champion": "Smolder",
        "TournamentLevel": "Secondary",
        "GameCount": "3",
        "Link": "RampageGG"
    },
    {
        "OverviewPage": "1ssue",
        "Champion": "Smolder",
        "TournamentLevel": "Secondary",
        "GameCount": "5",
        "Link": "1ssue"
    },
    {
        "OverviewPage": "1xn",
        "Champion": "Smolder",
        "TournamentLevel": "Primary",
        "GameCount": "3",
        "Link": "1xn"
    },
    {
        "OverviewPage": "5kid",
        "Champion": "Smolder",
        "TournamentLevel": "Primary",
        "GameCount": "3",
        "Link": "5kid"
    },
    {
        "OverviewPage": "Able",
        "Champion": "Smolder",
        "TournamentLevel": "Primary",
        "GameCount": "1",
        "Link": "Able"
    },
    {
        "OverviewPage": "Abner",
        "Champion": "Smolder",
        "TournamentLevel": "Secondary",
        "GameCount": "2",
        "Link": "Abner"
    },
    {
        "OverviewPage": "Ace (Ignacio David Piaggio)",
        "Champion": "Smolder",
        "TournamentLevel": "Secondary",
        "GameCount": "1",
        "Link": "Ace0"
    },
    {
        "OverviewPage": "Aetinoth",
        "Champion": "Smolder",
        "TournamentLevel": "Secondary",
        "GameCount": "1",
        "Link": "Aetinoth"
    },
    {
        "OverviewPage": "Aggress1on",
        "Champion": "Smolder",
        "TournamentLevel": "Secondary",
        "GameCount": "2",
        "Link": "Aggress1on"
    },
    {
        "OverviewPage": "Ahn",
        "Champion": "Smolder",
        "TournamentLevel": "Primary",
        "GameCount": "2",
        "Link": "Ahn (An Shan-Ye)"
    },
    {
        "OverviewPage": "Aikawa",
        "Champion": "Smolder",
        "TournamentLevel": "Secondary",
        "GameCount": "1",
        "Link": "aikawa"
    },
    {
        "OverviewPage": "Aiming",
        "Champion": "Smolder",
        "TournamentLevel": "Primary",
        "GameCount": "2",
        "Link": "Aiming"
    },
    {
        "OverviewPage": "Airren",
        "Champion": "Smolder",
        "TournamentLevel": "Secondary",
        "GameCount": "4",
        "Link": "Airren"
    },
    {
        "OverviewPage": "Ajie",
        "Champion": "Smolder",
        "TournamentLevel": "Secondary",
        "GameCount": "5",
        "Link": "Ajie"
    },
    {
        "OverviewPage": "AJOSU",
        "Champion": "Smolder",
        "TournamentLevel": "Secondary",
        "GameCount": "1",
        "Link": "AJOSU"
    },
    {
        "OverviewPage": "Ajuxsy",
        "Champion": "Smolder",
        "TournamentLevel": "Secondary",
        "GameCount": "1",
        "Link": "Ajuxsy"
    },
    {
        "OverviewPage": "Aklass",
        "Champion": "Smolder",
        "TournamentLevel": "Secondary",
        "GameCount": "1",
        "Link": "AKLASS"
    },
    {
        "OverviewPage": "Aliplane",
        "Champion": "Smolder",
        "TournamentLevel": "Secondary",
        "GameCount": "1",
        "Link": "Aliplane"
    },
    {
        "OverviewPage": "ANDARIEL",
        "Champion": "Smolder",
        "TournamentLevel": "Secondary",
        "GameCount": "1",
        "Link": "ANDARIEL"
    },
    {
        "OverviewPage": "Antonio",
        "Champion": "Smolder",
        "TournamentLevel": "Secondary",
        "GameCount": "1",
        "Link": "Antonio"
    },
    {
        "OverviewPage": "Array",
        "Champion": "Smolder",
        "TournamentLevel": "Secondary",
        "GameCount": "4",
        "Link": "Array"
    },
    {
        "OverviewPage": "Artemis (Trần Quốc Hưng)",
        "Champion": "Smolder",
        "TournamentLevel": "Primary",
        "GameCount": "3",
        "Link": "Artemis (Trần Quốc Hưng)"
    },
    {
        "OverviewPage": "Assum",
        "Champion": "Smolder",
        "TournamentLevel": "Primary",
        "GameCount": "1",
        "Link": "Assum"
    },
    {
        "OverviewPage": "Avarice",
        "Champion": "Smolder",
        "TournamentLevel": "Secondary",
        "GameCount": "1",
        "Link": "Avarice"
    },
    {
        "OverviewPage": "Avra",
        "Champion": "Smolder",
        "TournamentLevel": "Secondary",
        "GameCount": "1",
        "Link": "Avra"
    },
    {
        "OverviewPage": "Axelent",
        "Champion": "Smolder",
        "TournamentLevel": "Secondary",
        "GameCount": "1",
        "Link": "Axelent"
    },
    {
        "OverviewPage": "Banye",
        "Champion": "Smolder",
        "TournamentLevel": "Secondary",
        "GameCount": "1",
        "Link": "banye"
    },
    {
        "OverviewPage": "BAO (Jeong Hyeon-woo)",
        "Champion": "Smolder",
        "TournamentLevel": "Secondary",
        "GameCount": "2",
        "Link": "BAO (Jeong Hyeon-woo)"
    },
    {
        "OverviewPage": "BbeNj",
        "Champion": "Smolder",
        "TournamentLevel": "Secondary",
        "GameCount": "1",
        "Link": "bbeNj"
    },
    {
        "OverviewPage": "BEAN (Louis Schmitz)",
        "Champion": "Smolder",
        "TournamentLevel": "Secondary",
        "GameCount": "2",
        "Link": "BEAN (Louis Schmitz)"
    },
    {
        "OverviewPage": "Benzz",
        "Champion": "Smolder",
        "TournamentLevel": "Secondary",
        "GameCount": "3",
        "Link": "Benzz"
    },
    {
        "OverviewPage": "Berserker (Kim Min-cheol)",
        "Champion": "Smolder",
        "TournamentLevel": "Primary",
        "GameCount": "1",
        "Link": "Berserker (Kim Min-cheol)"
    },
    {
        "OverviewPage": "Betty",
        "Champion": "Smolder",
        "TournamentLevel": "Primary",
        "GameCount": "4",
        "Link": "Betty"
    },
    {
        "OverviewPage": "Bibou",
        "Champion": "Smolder",
        "TournamentLevel": "Secondary",
        "GameCount": "2",
        "Link": "Bibou"
    },
    {
        "OverviewPage": "BlackVodka",
        "Champion": "Smolder",
        "TournamentLevel": "Secondary",
        "GameCount": "1",
        "Link": "BlackVodka"
    },
    {
        "OverviewPage": "Blue (Giorgos Iakovidis)",
        "Champion": "Smolder",
        "TournamentLevel": "Secondary",
        "GameCount": "2",
        "Link": "Blu3"
    },
    {
        "OverviewPage": "Brance",
        "Champion": "Smolder",
        "TournamentLevel": "Primary",
        "GameCount": "3",
        "Link": "Brance"
    },
    {
        "OverviewPage": "Broadcoma",
        "Champion": "Smolder",
        "TournamentLevel": "Secondary",
        "GameCount": "1",
        "Link": "Broadcoma"
    },
    {
        "OverviewPage": "Bull",
        "Champion": "Smolder",
        "TournamentLevel": "Primary",
        "GameCount": "3",
        "Link": "Bull"
    },
    {
        "OverviewPage": "Caliste",
        "Champion": "Smolder",
        "TournamentLevel": "Secondary",
        "GameCount": "4",
        "Link": "Caliste"
    },
    {
        "OverviewPage": "Caltys",
        "Champion": "Smolder",
        "TournamentLevel": "Secondary",
        "GameCount": "2",
        "Link": "Caltys"
    },
    {
        "OverviewPage": "Carzzy",
        "Champion": "Smolder",
        "TournamentLevel": "Primary",
        "GameCount": "1",
        "Link": "Carzzy"
    },
    {
        "OverviewPage": "Celo",
        "Champion": "Smolder",
        "TournamentLevel": "Primary",
        "GameCount": "1",
        "Link": "Celo"
    },
    {
        "OverviewPage": "Certified",
        "Champion": "Smolder",
        "TournamentLevel": "Secondary",
        "GameCount": "1",
        "Link": "Certified"
    },
    {
        "OverviewPage": "CHECKFIDER",
        "Champion": "Smolder",
        "TournamentLevel": "Secondary",
        "GameCount": "1",
        "Link": "CHECKFIDER"
    },
    {
        "OverviewPage": "Cheng9",
        "Champion": "Smolder",
        "TournamentLevel": "Primary",
        "GameCount": "2",
        "Link": "Cheng9"
    },
    {
        "OverviewPage": "ChiCh1",
        "Champion": "Smolder",
        "TournamentLevel": "Primary",
        "GameCount": "3",
        "Link": "ChiCh1"
    },
    {
        "OverviewPage": "Chico (Hibiki Yamane)",
        "Champion": "Smolder",
        "TournamentLevel": "Secondary",
        "GameCount": "1",
        "Link": "chico (Hibiki Yamane)"
    },
    {
        "OverviewPage": "Chips (Gong Jia-Hao)",
        "Champion": "Smolder",
        "TournamentLevel": "Secondary",
        "GameCount": "1",
        "Link": "chips (Gong Jia-Hao)"
    },
    {
        "OverviewPage": "Cinna",
        "Champion": "Smolder",
        "TournamentLevel": "Secondary",
        "GameCount": "1",
        "Link": "Cinna"
    },
    {
        "OverviewPage": "Cirilo",
        "Champion": "Smolder",
        "TournamentLevel": "Secondary",
        "GameCount": "5",
        "Link": "Cirilo"
    },
    {
        "OverviewPage": "Cloud2",
        "Champion": "Smolder",
        "TournamentLevel": "Secondary",
        "GameCount": "1",
        "Link": "Cloud2"
    },
    {
        "OverviewPage": "CR0WN",
        "Champion": "Smolder",
        "TournamentLevel": "Secondary",
        "GameCount": "1",
        "Link": "Cr0wn"
    },
    {
        "OverviewPage": "Crowno",
        "Champion": "Smolder",
        "TournamentLevel": "Secondary",
        "GameCount": "1",
        "Link": "CrowYes"
    },
    {
        "OverviewPage": "Cryscata",
        "Champion": "Smolder",
        "TournamentLevel": "Primary",
        "GameCount": "3",
        "Link": "Cryscata"
    },
    {
        "OverviewPage": "Cute",
        "Champion": "Smolder",
        "TournamentLevel": "Secondary",
        "GameCount": "1",
        "Link": "cute"
    },
    {
        "OverviewPage": "CyraXx",
        "Champion": "Smolder",
        "TournamentLevel": "Secondary",
        "GameCount": "2",
        "Link": "cyraXx"
    },
    {
        "OverviewPage": "Daksider",
        "Champion": "Smolder",
        "TournamentLevel": "Secondary",
        "GameCount": "3",
        "Link": "Daksider"
    },
    {
        "OverviewPage": "DANY",
        "Champion": "Smolder",
        "TournamentLevel": "Secondary",
        "GameCount": "2",
        "Link": "DANY"
    },
    {
        "OverviewPage": "Dawidsonek",
        "Champion": "Smolder",
        "TournamentLevel": "Secondary",
        "GameCount": "3",
        "Link": "Dawidsonek"
    },
    {
        "OverviewPage": "Deadhound",
        "Champion": "Smolder",
        "TournamentLevel": "Secondary",
        "GameCount": "2",
        "Link": "Deadhound"
    },
    {
        "OverviewPage": "Deadly",
        "Champion": "Smolder",
        "TournamentLevel": "Secondary",
        "GameCount": "2",
        "Link": "Deadly"
    },
    {
        "OverviewPage": "Deant",
        "Champion": "Smolder",
        "TournamentLevel": "Secondary",
        "GameCount": "1",
        "Link": "Deant"
    },
    {
        "OverviewPage": "Deft",
        "Champion": "Smolder",
        "TournamentLevel": "Primary",
        "GameCount": "3",
        "Link": "Deft"
    },
    {
        "OverviewPage": "Dejw",
        "Champion": "Smolder",
        "TournamentLevel": "Secondary",
        "GameCount": "1",
        "Link": "Dejw"
    },
    {
        "OverviewPage": "DenVoksne",
        "Champion": "Smolder",
        "TournamentLevel": "Secondary",
        "GameCount": "2",
        "Link": "DenVoksne"
    },
    {
        "OverviewPage": "Deokdam",
        "Champion": "Smolder",
        "TournamentLevel": "Primary",
        "GameCount": "1",
        "Link": "deokdam"
    },
    {
        "OverviewPage": "Devin",
        "Champion": "Smolder",
        "TournamentLevel": "Secondary",
        "GameCount": "1",
        "Link": "Devin"
    },
    {
        "OverviewPage": "Diable",
        "Champion": "Smolder",
        "TournamentLevel": "Secondary",
        "GameCount": "1",
        "Link": "Diable"
    },
    {
        "OverviewPage": "Did",
        "Champion": "Smolder",
        "TournamentLevel": "Secondary",
        "GameCount": "1",
        "Link": "Did"
    },
    {
        "OverviewPage": "Didi",
        "Champion": "Smolder",
        "TournamentLevel": "Secondary",
        "GameCount": "1",
        "Link": "DIDl"
    },
    {
        "OverviewPage": "Diva",
        "Champion": "Smolder",
        "TournamentLevel": "Secondary",
        "GameCount": "1",
        "Link": "Diva"
    },
    {
        "OverviewPage": "DizL",
        "Champion": "Smolder",
        "TournamentLevel": "Secondary",
        "GameCount": "1",
        "Link": "DizL"
    },
    {
        "OverviewPage": "Dog2",
        "Champion": "Smolder",
        "TournamentLevel": "Secondary",
        "GameCount": "1",
        "Link": "dog2"
    },
    {
        "OverviewPage": "Doggo",
        "Champion": "Smolder",
        "TournamentLevel": "Primary",
        "GameCount": "3",
        "Link": "Doggo"
    },
    {
        "OverviewPage": "DoTmm",
        "Champion": "Smolder",
        "TournamentLevel": "Secondary",
        "GameCount": "1",
        "Link": "DoTmm"
    },
    {
        "OverviewPage": "Dreilix",
        "Champion": "Smolder",
        "TournamentLevel": "Secondary",
        "GameCount": "1",
        "Link": "Dreilix"
    },
    {
        "OverviewPage": "Dzeffry",
        "Champion": "Smolder",
        "TournamentLevel": "Secondary",
        "GameCount": "1",
        "Link": "Dzeffry"
    },
    {
        "OverviewPage": "Dzejno",
        "Champion": "Smolder",
        "TournamentLevel": "Secondary",
        "GameCount": "2",
        "Link": "Dzejno"
    },
    {
        "OverviewPage": "EasyLove",
        "Champion": "Smolder",
        "TournamentLevel": "Primary",
        "GameCount": "3",
        "Link": "EasyLove"
    },
    {
        "OverviewPage": "Eddie",
        "Champion": "Smolder",
        "TournamentLevel": "Primary",
        "GameCount": "2",
        "Link": "Eddie"
    },
    {
        "OverviewPage": "Electro (Jens De Vos)",
        "Champion": "Smolder",
        "TournamentLevel": "Secondary",
        "GameCount": "1",
        "Link": "Electro (Jens De Vos)"
    },
    {
        "OverviewPage": "Elk",
        "Champion": "Smolder",
        "TournamentLevel": "Primary",
        "GameCount": "4",
        "Link": "elk"
    },
    {
        "OverviewPage": "Empty (Damian Guilherme)",
        "Champion": "Smolder",
        "TournamentLevel": "Secondary",
        "GameCount": "1",
        "Link": "Emptyy"
    },
    {
        "OverviewPage": "Enosh",
        "Champion": "Smolder",
        "TournamentLevel": "Secondary",
        "GameCount": "4",
        "Link": "Enosh"
    },
    {
        "OverviewPage": "Enthralled",
        "Champion": "Smolder",
        "TournamentLevel": "Secondary",
        "GameCount": "2",
        "Link": "Enthralled"
    },
    {
        "OverviewPage": "Envyy",
        "Champion": "Smolder",
        "TournamentLevel": "Primary",
        "GameCount": "7",
        "Link": "Envyy"
    },
    {
        "OverviewPage": "Esko",
        "Champion": "Smolder",
        "TournamentLevel": "Secondary",
        "GameCount": "4",
        "Link": "Esko"
    },
    {
        "OverviewPage": "Etoo",
        "Champion": "Smolder",
        "TournamentLevel": "Secondary",
        "GameCount": "1",
        "Link": "Etoo"
    },
    {
        "OverviewPage": "Evi",
        "Champion": "Smolder",
        "TournamentLevel": "Primary",
        "GameCount": "2",
        "Link": "Evi"
    },
    {
        "OverviewPage": "Evol",
        "Champion": "Smolder",
        "TournamentLevel": "Secondary",
        "GameCount": "2",
        "Link": "evol"
    },
    {
        "OverviewPage": "Exduardo",
        "Champion": "Smolder",
        "TournamentLevel": "Secondary",
        "GameCount": "2",
        "Link": "Exduardo"
    },
    {
        "OverviewPage": "Exnom",
        "Champion": "Smolder",
        "TournamentLevel": "Secondary",
        "GameCount": "1",
        "Link": "Exnom"
    },
    {
        "OverviewPage": "Fatihcan",
        "Champion": "Smolder",
        "TournamentLevel": "Secondary",
        "GameCount": "1",
        "Link": "Fatihcan"
    },
    {
        "OverviewPage": "FBI",
        "Champion": "Smolder",
        "TournamentLevel": "Primary",
        "GameCount": "2",
        "Link": "FBI"
    },
    {
        "OverviewPage": "Fede",
        "Champion": "Smolder",
        "TournamentLevel": "Secondary",
        "GameCount": "1",
        "Link": "Fede"
    },
    {
        "OverviewPage": "Feng (Chen Chun-Feng)",
        "Champion": "Smolder",
        "TournamentLevel": "Primary",
        "GameCount": "1",
        "Link": "Feng (Chen Chun-Feng)"
    },
    {
        "OverviewPage": "Flakked",
        "Champion": "Smolder",
        "TournamentLevel": "Primary",
        "GameCount": "1",
        "Link": "Flakked"
    },
    {
        "OverviewPage": "FlickeR (Rodrigo de Oliveira)",
        "Champion": "Smolder",
        "TournamentLevel": "Secondary",
        "GameCount": "2",
        "Link": "FlickeR (Rodrigo de Oliveira)"
    },
    {
        "OverviewPage": "Focuss",
        "Champion": "Smolder",
        "TournamentLevel": "Secondary",
        "GameCount": "1",
        "Link": "Focuss"
    },
    {
        "OverviewPage": "Frappii",
        "Champion": "Smolder",
        "TournamentLevel": "Secondary",
        "GameCount": "2",
        "Link": "Frappii"
    },
    {
        "OverviewPage": "Fruity Fresh",
        "Champion": "Smolder",
        "TournamentLevel": "Secondary",
        "GameCount": "1",
        "Link": "Fruity Fresh"
    },
    {
        "OverviewPage": "Fun K3y",
        "Champion": "Smolder",
        "TournamentLevel": "Secondary",
        "GameCount": "1",
        "Link": "Fun K3y"
    },
    {
        "OverviewPage": "Fynox",
        "Champion": "Smolder",
        "TournamentLevel": "Secondary",
        "GameCount": "2",
        "Link": "Fynox"
    },
    {
        "OverviewPage": "GALA",
        "Champion": "Smolder",
        "TournamentLevel": "Primary",
        "GameCount": "2",
        "Link": "GALA"
    },
    {
        "OverviewPage": "Gavotto",
        "Champion": "Smolder",
        "TournamentLevel": "Primary",
        "GameCount": "4",
        "Link": "Gavotto"
    },
    {
        "OverviewPage": "GGiler",
        "Champion": "Smolder",
        "TournamentLevel": "Secondary",
        "GameCount": "1",
        "Link": "GGiler"
    },
    {
        "OverviewPage": "GodJJ",
        "Champion": "Smolder",
        "TournamentLevel": "Primary",
        "GameCount": "1",
        "Link": "GodJJ"
    },
    {
        "OverviewPage": "Goose (Kerem Katilmis)",
        "Champion": "Smolder",
        "TournamentLevel": "Secondary",
        "GameCount": "1",
        "Link": "goose (Kerem Katilmis)"
    },
    {
        "OverviewPage": "Gravepast",
        "Champion": "Smolder",
        "TournamentLevel": "Secondary",
        "GameCount": "1",
        "Link": "Gravepast"
    },
    {
        "OverviewPage": "Gumayusi",
        "Champion": "Smolder",
        "TournamentLevel": "Primary",
        "GameCount": "1",
        "Link": "Gumayusi"
    },
    {
        "OverviewPage": "Guppy",
        "Champion": "Smolder",
        "TournamentLevel": "Secondary",
        "GameCount": "1",
        "Link": "Guppy"
    },
    {
        "OverviewPage": "Guubi",
        "Champion": "Smolder",
        "TournamentLevel": "Secondary",
        "GameCount": "1",
        "Link": "Guubi"
    },
    {
        "OverviewPage": "Hans Sama",
        "Champion": "Smolder",
        "TournamentLevel": "Primary",
        "GameCount": "2",
        "Link": "Hans Sama"
    },
    {
        "OverviewPage": "Hans SamD",
        "Champion": "Smolder",
        "TournamentLevel": "Secondary",
        "GameCount": "4",
        "Link": "Hans SamD"
    },
    {
        "OverviewPage": "HARPOON",
        "Champion": "Smolder",
        "TournamentLevel": "Secondary",
        "GameCount": "2",
        "Link": "HARPOON"
    },
    {
        "OverviewPage": "Hatrixx",
        "Champion": "Smolder",
        "TournamentLevel": "Secondary",
        "GameCount": "1",
        "Link": "Hatrixx"
    },
    {
        "OverviewPage": "Hax",
        "Champion": "Smolder",
        "TournamentLevel": "Secondary",
        "GameCount": "1",
        "Link": "Hax"
    },
    {
        "OverviewPage": "Hazel (Costin Pestrițu)",
        "Champion": "Smolder",
        "TournamentLevel": "Secondary",
        "GameCount": "1",
        "Link": "Hazel (Costin Pestrițu)"
    },
    {
        "OverviewPage": "Hena",
        "Champion": "Smolder",
        "TournamentLevel": "Primary",
        "GameCount": "2",
        "Link": "Hena"
    },
    {
        "OverviewPage": "Hermes (Lin You-Ju)",
        "Champion": "Smolder",
        "TournamentLevel": "Secondary",
        "GameCount": "4",
        "Link": "Hermes (Lin You-Ju)"
    },
    {
        "OverviewPage": "Hid0",
        "Champion": "Smolder",
        "TournamentLevel": "Secondary",
        "GameCount": "3",
        "Link": "Hid0"
    },
    {
        "OverviewPage": "HolyPhoenix",
        "Champion": "Smolder",
        "TournamentLevel": "Secondary",
        "GameCount": "1",
        "Link": "HolyPhoenix"
    },
    {
        "OverviewPage": "Hope (Wang Jie)",
        "Champion": "Smolder",
        "TournamentLevel": "Primary",
        "GameCount": "2",
        "Link": "Hope (Wang Jie)"
    },
    {
        "OverviewPage": "Ibai (Ibai Yuste Martin)",
        "Champion": "Smolder",
        "TournamentLevel": "Secondary",
        "GameCount": "2",
        "Link": "Ibai (Ibai Yuste Martin)"
    },
    {
        "OverviewPage": "Improve",
        "Champion": "Smolder",
        "TournamentLevel": "Secondary",
        "GameCount": "1",
        "Link": "Improve"
    },
    {
        "OverviewPage": "Innaxe",
        "Champion": "Smolder",
        "TournamentLevel": "Secondary",
        "GameCount": "1",
        "Link": "Innaxe"
    },
    {
        "OverviewPage": "InoriB",
        "Champion": "Smolder",
        "TournamentLevel": "Secondary",
        "GameCount": "1",
        "Link": "InoriB"
    },
    {
        "OverviewPage": "IntoxqZz",
        "Champion": "Smolder",
        "TournamentLevel": "Secondary",
        "GameCount": "1",
        "Link": "IntoxqZz"
    },
    {
        "OverviewPage": "IvanD",
        "Champion": "Smolder",
        "TournamentLevel": "Secondary",
        "GameCount": "1",
        "Link": "IvanD"
    },
    {
        "OverviewPage": "Iwanan",
        "Champion": "Smolder",
        "TournamentLevel": "Secondary",
        "GameCount": "2",
        "Link": "iwanan"
    },
    {
        "OverviewPage": "Jabuticaba",
        "Champion": "Smolder",
        "TournamentLevel": "Secondary",
        "GameCount": "1",
        "Link": "Jabuticaba"
    },
    {
        "OverviewPage": "JackeyLove",
        "Champion": "Smolder",
        "TournamentLevel": "Primary",
        "GameCount": "2",
        "Link": "JackeyLove"
    },
    {
        "OverviewPage": "Jackspektra",
        "Champion": "Smolder",
        "TournamentLevel": "Secondary",
        "GameCount": "2",
        "Link": "Jackspektra"
    },
    {
        "OverviewPage": "Jamie (Evgeny Sorokin)",
        "Champion": "Smolder",
        "TournamentLevel": "Secondary",
        "GameCount": "1",
        "Link": "Jamie (Evgeny Sorokin)"
    },
    {
        "OverviewPage": "Jeskla",
        "Champion": "Smolder",
        "TournamentLevel": "Secondary",
        "GameCount": "2",
        "Link": "Jeskla"
    },
    {
        "OverviewPage": "Jezu",
        "Champion": "Smolder",
        "TournamentLevel": "Secondary",
        "GameCount": "4",
        "Link": "Jezu"
    },
    {
        "OverviewPage": "JiaQi",
        "Champion": "Smolder",
        "TournamentLevel": "Secondary",
        "GameCount": "2",
        "Link": "JiaQi"
    },
    {
        "OverviewPage": "Jimsnop",
        "Champion": "Smolder",
        "TournamentLevel": "Secondary",
        "GameCount": "1",
        "Link": "jimsnop"
    },
    {
        "OverviewPage": "Jinjo",
        "Champion": "Smolder",
        "TournamentLevel": "Secondary",
        "GameCount": "2",
        "Link": "jinjo"
    },
    {
        "OverviewPage": "Jiwoo",
        "Champion": "Smolder",
        "TournamentLevel": "Primary",
        "GameCount": "4",
        "Link": "Jiwoo"
    },
    {
        "OverviewPage": "Jopa",
        "Champion": "Smolder",
        "TournamentLevel": "Secondary",
        "GameCount": "3",
        "Link": "Jopa"
    },
    {
        "OverviewPage": "Jujutw0",
        "Champion": "Smolder",
        "TournamentLevel": "Secondary",
        "GameCount": "2",
        "Link": "JuJuTw0"
    },
    {
        "OverviewPage": "Juliera",
        "Champion": "Smolder",
        "TournamentLevel": "Secondary",
        "GameCount": "2",
        "Link": "Juliera"
    },
    {
        "OverviewPage": "K1ng",
        "Champion": "Smolder",
        "TournamentLevel": "Primary",
        "GameCount": "4",
        "Link": "k1ng"
    },
    {
        "OverviewPage": "Kachu",
        "Champion": "Smolder",
        "TournamentLevel": "Secondary",
        "GameCount": "1",
        "Link": "Kachu"
    },
    {
        "OverviewPage": "Kaii",
        "Champion": "Smolder",
        "TournamentLevel": "Secondary",
        "GameCount": "1",
        "Link": "Kaii1"
    },
    {
        "OverviewPage": "Kangin",
        "Champion": "Smolder",
        "TournamentLevel": "Secondary",
        "GameCount": "1",
        "Link": "Kangin"
    },
    {
        "OverviewPage": "Kaori",
        "Champion": "Smolder",
        "TournamentLevel": "Secondary",
        "GameCount": "1",
        "Link": "Kaori"
    },
    {
        "OverviewPage": "Keater",
        "Champion": "Smolder",
        "TournamentLevel": "Secondary",
        "GameCount": "1",
        "Link": "keater"
    },
    {
        "OverviewPage": "Keduii",
        "Champion": "Smolder",
        "TournamentLevel": "Secondary",
        "GameCount": "1",
        "Link": "Keduii"
    },
    {
        "OverviewPage": "Kehvo",
        "Champion": "Smolder",
        "TournamentLevel": "Secondary",
        "GameCount": "5",
        "Link": "Kehvo"
    },
    {
        "OverviewPage": "Kenal",
        "Champion": "Smolder",
        "TournamentLevel": "Secondary",
        "GameCount": "2",
        "Link": "Kenal"
    },
    {
        "OverviewPage": "KERUSHA",
        "Champion": "Smolder",
        "TournamentLevel": "Secondary",
        "GameCount": "2",
        "Link": "KERUSHA"
    },
    {
        "OverviewPage": "Kerveros",
        "Champion": "Smolder",
        "TournamentLevel": "Secondary",
        "GameCount": "2",
        "Link": "Kerveros"
    },
    {
        "OverviewPage": "Khaydarin",
        "Champion": "Smolder",
        "TournamentLevel": "Secondary",
        "GameCount": "1",
        "Link": "Khaydarin"
    },
    {
        "OverviewPage": "Kiaya",
        "Champion": "Smolder",
        "TournamentLevel": "Primary",
        "GameCount": "1",
        "Link": "Kiaya"
    },
    {
        "OverviewPage": "Kiefer",
        "Champion": "Smolder",
        "TournamentLevel": "Primary",
        "GameCount": "1",
        "Link": "Kiefer"
    },
    {
        "OverviewPage": "Kingen",
        "Champion": "Smolder",
        "TournamentLevel": "Primary",
        "GameCount": "1",
        "Link": "Kingen"
    },
    {
        "OverviewPage": "KNEZA",
        "Champion": "Smolder",
        "TournamentLevel": "Secondary",
        "GameCount": "2",
        "Link": "KNEZA"
    },
    {
        "OverviewPage": "Kz (Nicolás Gutiérrez)",
        "Champion": "Smolder",
        "TournamentLevel": "Primary",
        "GameCount": "2",
        "Link": "Kz (Nicolás Gutiérrez)"
    },
    {
        "OverviewPage": "Lac",
        "Champion": "Smolder",
        "TournamentLevel": "Primary",
        "GameCount": "2",
        "Link": "Lac"
    },
    {
        "OverviewPage": "Lamb",
        "Champion": "Smolder",
        "TournamentLevel": "Secondary",
        "GameCount": "1",
        "Link": "lamb"
    },
    {
        "OverviewPage": "Lancelot Link",
        "Champion": "Smolder",
        "TournamentLevel": "Secondary",
        "GameCount": "1",
        "Link": "Lancelot Link"
    },
    {
        "OverviewPage": "Later",
        "Champion": "Smolder",
        "TournamentLevel": "Secondary",
        "GameCount": "2",
        "Link": "Later"
    },
    {
        "OverviewPage": "Leandrinn",
        "Champion": "Smolder",
        "TournamentLevel": "Secondary",
        "GameCount": "3",
        "Link": "Leandrinn"
    },
    {
        "OverviewPage": "Leave",
        "Champion": "Smolder",
        "TournamentLevel": "Secondary",
        "GameCount": "1",
        "Link": "Leave"
    },
    {
        "OverviewPage": "Leemas",
        "Champion": "Smolder",
        "TournamentLevel": "Primary",
        "GameCount": "5",
        "Link": "leemas"
    },
    {
        "OverviewPage": "Legolas",
        "Champion": "Smolder",
        "TournamentLevel": "Secondary",
        "GameCount": "3",
        "Link": "Legolas"
    },
    {
        "OverviewPage": "Lenom",
        "Champion": "Smolder",
        "TournamentLevel": "Secondary",
        "GameCount": "1",
        "Link": "Lenom"
    },
    {
        "OverviewPage": "Lens",
        "Champion": "Smolder",
        "TournamentLevel": "Secondary",
        "GameCount": "1",
        "Link": "Lens"
    },
    {
        "OverviewPage": "Leo (Han Gyeo-re)",
        "Champion": "Smolder",
        "TournamentLevel": "Secondary",
        "GameCount": "1",
        "Link": "Leo (Han Gyeo-re)"
    },
    {
        "OverviewPage": "Lethe",
        "Champion": "Smolder",
        "TournamentLevel": "Secondary",
        "GameCount": "1",
        "Link": "lethe"
    },
    {
        "OverviewPage": "Leventor",
        "Champion": "Smolder",
        "TournamentLevel": "Secondary",
        "GameCount": "1",
        "Link": "Leventor"
    },
    {
        "OverviewPage": "Levitate",
        "Champion": "Smolder",
        "TournamentLevel": "Secondary",
        "GameCount": "1",
        "Link": "Levitate"
    },
    {
        "OverviewPage": "Lo33v",
        "Champion": "Smolder",
        "TournamentLevel": "Secondary",
        "GameCount": "3",
        "Link": "lo33v"
    },
    {
        "OverviewPage": "Looki",
        "Champion": "Smolder",
        "TournamentLevel": "Secondary",
        "GameCount": "1",
        "Link": "looki"
    },
    {
        "OverviewPage": "Lotus (Ignatios Psarros)",
        "Champion": "Smolder",
        "TournamentLevel": "Secondary",
        "GameCount": "2",
        "Link": "Lotus (Ignatios Psarros)"
    },
    {
        "OverviewPage": "Lucker",
        "Champion": "Smolder",
        "TournamentLevel": "Secondary",
        "GameCount": "1",
        "Link": "Lucker"
    },
    {
        "OverviewPage": "Luger",
        "Champion": "Smolder",
        "TournamentLevel": "Secondary",
        "GameCount": "1",
        "Link": "LUGER"
    },
    {
        "OverviewPage": "Lure (Shin Jae-yoon)",
        "Champion": "Smolder",
        "TournamentLevel": "Secondary",
        "GameCount": "4",
        "Link": "Lure (Shin Jae-yoon)"
    },
    {
        "OverviewPage": "Lwx",
        "Champion": "Smolder",
        "TournamentLevel": "Primary",
        "GameCount": "3",
        "Link": "Lwx"
    },
    {
        "OverviewPage": "M0NK",
        "Champion": "Smolder",
        "TournamentLevel": "Secondary",
        "GameCount": "1",
        "Link": "Monk (Joosep Kivilaan)"
    },
    {
        "OverviewPage": "Maged",
        "Champion": "Smolder",
        "TournamentLevel": "Secondary",
        "GameCount": "1",
        "Link": "Maged"
    },
    {
        "OverviewPage": "Maikehan",
        "Champion": "Smolder",
        "TournamentLevel": "Secondary",
        "GameCount": "1",
        "Link": "Maikehan"
    },
    {
        "OverviewPage": "Manolete",
        "Champion": "Smolder",
        "TournamentLevel": "Secondary",
        "GameCount": "1",
        "Link": "Manolete"
    },
    {
        "OverviewPage": "Marble",
        "Champion": "Smolder",
        "TournamentLevel": "Primary",
        "GameCount": "1",
        "Link": "Marble"
    },
    {
        "OverviewPage": "Marvin",
        "Champion": "Smolder",
        "TournamentLevel": "Secondary",
        "GameCount": "1",
        "Link": "Marvin"
    },
    {
        "OverviewPage": "Marzo",
        "Champion": "Smolder",
        "TournamentLevel": "Secondary",
        "GameCount": "2",
        "Link": "Marzo"
    },
    {
        "OverviewPage": "Massu",
        "Champion": "Smolder",
        "TournamentLevel": "Primary",
        "GameCount": "1",
        "Link": "Massu"
    },
    {
        "OverviewPage": "Matias",
        "Champion": "Smolder",
        "TournamentLevel": "Secondary",
        "GameCount": "2",
        "Link": "Matias"
    },
    {
        "OverviewPage": "Meech",
        "Champion": "Smolder",
        "TournamentLevel": "Primary",
        "GameCount": "2",
        "Link": "Meech"
    },
    {
        "OverviewPage": "Mentos",
        "Champion": "Smolder",
        "TournamentLevel": "Secondary",
        "GameCount": "1",
        "Link": "Mentos"
    },
    {
        "OverviewPage": "Messages",
        "Champion": "Smolder",
        "TournamentLevel": "Secondary",
        "GameCount": "2",
        "Link": "Messages"
    },
    {
        "OverviewPage": "MetroArcher",
        "Champion": "Smolder",
        "TournamentLevel": "Secondary",
        "GameCount": "1",
        "Link": "MetroArcher"
    },
    {
        "OverviewPage": "MicaO",
        "Champion": "Smolder",
        "TournamentLevel": "Primary",
        "GameCount": "3",
        "Link": "micaO"
    },
    {
        "OverviewPage": "Milkcat",
        "Champion": "Smolder",
        "TournamentLevel": "Secondary",
        "GameCount": "1",
        "Link": "Milkcat"
    },
    {
        "OverviewPage": "Mimic (Nawaf Al-Salem)",
        "Champion": "Smolder",
        "TournamentLevel": "Secondary",
        "GameCount": "1",
        "Link": "Mimic1"
    },
    {
        "OverviewPage": "Mind",
        "Champion": "Smolder",
        "TournamentLevel": "Secondary",
        "GameCount": "2",
        "Link": "Mind"
    },
    {
        "OverviewPage": "Mindrago",
        "Champion": "Smolder",
        "TournamentLevel": "Secondary",
        "GameCount": "3",
        "Link": "Mindrago"
    },
    {
        "OverviewPage": "Minui",
        "Champion": "Smolder",
        "TournamentLevel": "Secondary",
        "GameCount": "2",
        "Link": "Minui"
    },
    {
        "OverviewPage": "Mirbs",
        "Champion": "Smolder",
        "TournamentLevel": "Secondary",
        "GameCount": "1",
        "Link": "Mirbs"
    },
    {
        "OverviewPage": "Mireu",
        "Champion": "Smolder",
        "TournamentLevel": "Secondary",
        "GameCount": "1",
        "Link": "Mireu"
    },
    {
        "OverviewPage": "Mishigu",
        "Champion": "Smolder",
        "TournamentLevel": "Secondary",
        "GameCount": "2",
        "Link": "Mishigu"
    },
    {
        "OverviewPage": "Mist (Rhod Aian Michael Rosario)",
        "Champion": "Smolder",
        "TournamentLevel": "Secondary",
        "GameCount": "1",
        "Link": "Mist (Rhod Aian Michael Rosario)"
    },
    {
        "OverviewPage": "MKL",
        "Champion": "Smolder",
        "TournamentLevel": "Secondary",
        "GameCount": "2",
        "Link": "MKL"
    },
    {
        "OverviewPage": "MnM (Wong Ka Chun)",
        "Champion": "Smolder",
        "TournamentLevel": "Primary",
        "GameCount": "2",
        "Link": "MnM (Wong Ka Chun)"
    },
    {
        "OverviewPage": "Morttheus",
        "Champion": "Smolder",
        "TournamentLevel": "Secondary",
        "GameCount": "4",
        "Link": "Morttheus"
    },
    {
        "OverviewPage": "MrPhant0m",
        "Champion": "Smolder",
        "TournamentLevel": "Secondary",
        "GameCount": "1",
        "Link": "MrPhant0m"
    },
    {
        "OverviewPage": "Mumek",
        "Champion": "Smolder",
        "TournamentLevel": "Secondary",
        "GameCount": "1",
        "Link": "mumek"
    },
    {
        "OverviewPage": "Mune",
        "Champion": "Smolder",
        "TournamentLevel": "Secondary",
        "GameCount": "1",
        "Link": "Mune"
    },
    {
        "OverviewPage": "Namex",
        "Champion": "Smolder",
        "TournamentLevel": "Secondary",
        "GameCount": "2",
        "Link": "Namex"
    },
    {
        "OverviewPage": "Nawaf",
        "Champion": "Smolder",
        "TournamentLevel": "Secondary",
        "GameCount": "2",
        "Link": "Nawaf"
    },
    {
        "OverviewPage": "Neon (Matúš Jakubčík)",
        "Champion": "Smolder",
        "TournamentLevel": "Secondary",
        "GameCount": "3",
        "Link": "Neon (Matúš Jakubčík)"
    },
    {
        "OverviewPage": "Netuno",
        "Champion": "Smolder",
        "TournamentLevel": "Primary",
        "GameCount": "1",
        "Link": "Netuno"
    },
    {
        "OverviewPage": "Nikiyas",
        "Champion": "Smolder",
        "TournamentLevel": "Secondary",
        "GameCount": "1",
        "Link": "Nikiyas"
    },
    {
        "OverviewPage": "NinjaSenpai",
        "Champion": "Smolder",
        "TournamentLevel": "Secondary",
        "GameCount": "1",
        "Link": "NinjaSenpai"
    },
    {
        "OverviewPage": "Nite (Ardian Spahiu)",
        "Champion": "Smolder",
        "TournamentLevel": "Secondary",
        "GameCount": "2",
        "Link": "Nite (Ardian Spahiu)"
    },
    {
        "OverviewPage": "Nomad (Eymen Alan)",
        "Champion": "Smolder",
        "TournamentLevel": "Secondary",
        "GameCount": "1",
        "Link": "Nomad (Eymen Alan)"
    },
    {
        "OverviewPage": "Notiko",
        "Champion": "Smolder",
        "TournamentLevel": "Secondary",
        "GameCount": "2",
        "Link": "Notiko"
    },
    {
        "OverviewPage": "NuQ",
        "Champion": "Smolder",
        "TournamentLevel": "Secondary",
        "GameCount": "1",
        "Link": "NuQ"
    },
    {
        "OverviewPage": "Odysseia",
        "Champion": "Smolder",
        "TournamentLevel": "Secondary",
        "GameCount": "2",
        "Link": "Odysseia"
    },
    {
        "OverviewPage": "Omibro",
        "Champion": "Smolder",
        "TournamentLevel": "Secondary",
        "GameCount": "2",
        "Link": "Omibro"
    },
    {
        "OverviewPage": "OMON",
        "Champion": "Smolder",
        "TournamentLevel": "Secondary",
        "GameCount": "1",
        "Link": "OMON"
    },
    {
        "OverviewPage": "On3Sh0t",
        "Champion": "Smolder",
        "TournamentLevel": "Secondary",
        "GameCount": "2",
        "Link": "On3Sh0t"
    },
    {
        "OverviewPage": "Orion (Alan Roger)",
        "Champion": "Smolder",
        "TournamentLevel": "Secondary",
        "GameCount": "1",
        "Link": "Orion (Alan Roger)"
    },
    {
        "OverviewPage": "Ozgur (Özgür Umut Kars)",
        "Champion": "Smolder",
        "TournamentLevel": "Secondary",
        "GameCount": "1",
        "Link": "Ozgur (Özgür Umut Kars)"
    },
    {
        "OverviewPage": "Paduck",
        "Champion": "Smolder",
        "TournamentLevel": "Secondary",
        "GameCount": "6",
        "Link": "Paduck"
    },
    {
        "OverviewPage": "Paladin (Ivan Delač)",
        "Champion": "Smolder",
        "TournamentLevel": "Secondary",
        "GameCount": "1",
        "Link": "Paladin (Ivan Delač)"
    },
    {
        "OverviewPage": "Pangjin",
        "Champion": "Smolder",
        "TournamentLevel": "Secondary",
        "GameCount": "1",
        "Link": "Pangjin"
    },
    {
        "OverviewPage": "Paparotis",
        "Champion": "Smolder",
        "TournamentLevel": "Secondary",
        "GameCount": "1",
        "Link": "Paparotis"
    },
    {
        "OverviewPage": "Patrik",
        "Champion": "Smolder",
        "TournamentLevel": "Primary",
        "GameCount": "1",
        "Link": "Patrik"
    },
    {
        "OverviewPage": "Peyz",
        "Champion": "Smolder",
        "TournamentLevel": "Primary",
        "GameCount": "1",
        "Link": "Peyz"
    },
    {
        "OverviewPage": "Photic",
        "Champion": "Smolder",
        "TournamentLevel": "Primary",
        "GameCount": "1",
        "Link": "Photic"
    },
    {
        "OverviewPage": "Photon",
        "Champion": "Smolder",
        "TournamentLevel": "Primary",
        "GameCount": "1",
        "Link": "Photon"
    },
    {
        "OverviewPage": "PiOk",
        "Champion": "Smolder",
        "TournamentLevel": "Secondary",
        "GameCount": "3",
        "Link": "PiOk"
    },
    {
        "OverviewPage": "Piwek",
        "Champion": "Smolder",
        "TournamentLevel": "Secondary",
        "GameCount": "3",
        "Link": "Piwek"
    },
    {
        "OverviewPage": "PmK",
        "Champion": "Smolder",
        "TournamentLevel": "Secondary",
        "GameCount": "1",
        "Link": "PmK"
    },
    {
        "OverviewPage": "Pomo",
        "Champion": "Smolder",
        "TournamentLevel": "Secondary",
        "GameCount": "1",
        "Link": "Pomo"
    },
    {
        "OverviewPage": "Prage",
        "Champion": "Smolder",
        "TournamentLevel": "Primary",
        "GameCount": "1",
        "Link": "Prage"
    },
    {
        "OverviewPage": "Prince (Lee Chae-hwan)",
        "Champion": "Smolder",
        "TournamentLevel": "Primary",
        "GameCount": "1",
        "Link": "Prince (Lee Chae-hwan)"
    },
    {
        "OverviewPage": "Prismal",
        "Champion": "Smolder",
        "TournamentLevel": "Secondary",
        "GameCount": "1",
        "Link": "Prismal"
    },
    {
        "OverviewPage": "PTS",
        "Champion": "Smolder",
        "TournamentLevel": "Secondary",
        "GameCount": "4",
        "Link": "PTS"
    },
    {
        "OverviewPage": "Puddin",
        "Champion": "Smolder",
        "TournamentLevel": "Primary",
        "GameCount": "4",
        "Link": "Puddin"
    },
    {
        "OverviewPage": "Pyshiro",
        "Champion": "Smolder",
        "TournamentLevel": "Primary",
        "GameCount": "4",
        "Link": "Pyshiro"
    },
    {
        "OverviewPage": "Qingshui",
        "Champion": "Smolder",
        "TournamentLevel": "Secondary",
        "GameCount": "1",
        "Link": "Qingshui"
    },
    {
        "OverviewPage": "R0bbed",
        "Champion": "Smolder",
        "TournamentLevel": "Secondary",
        "GameCount": "1",
        "Link": "r0bbed"
    },
    {
        "OverviewPage": "Ragnarr",
        "Champion": "Smolder",
        "TournamentLevel": "Secondary",
        "GameCount": "2",
        "Link": "Ragnarr"
    },
    {
        "OverviewPage": "Renas",
        "Champion": "Smolder",
        "TournamentLevel": "Secondary",
        "GameCount": "1",
        "Link": "Renas"
    },
    {
        "OverviewPage": "Rend (Paris Liadis)",
        "Champion": "Smolder",
        "TournamentLevel": "Secondary",
        "GameCount": "2",
        "Link": "Rend (Paris Liadis)"
    },
    {
        "OverviewPage": "Rise",
        "Champion": "Smolder",
        "TournamentLevel": "Secondary",
        "GameCount": "1",
        "Link": "Rise"
    },
    {
        "OverviewPage": "RJS",
        "Champion": "Smolder",
        "TournamentLevel": "Secondary",
        "GameCount": "1",
        "Link": "RJS"
    },
    {
        "OverviewPage": "Roison",
        "Champion": "Smolder",
        "TournamentLevel": "Secondary",
        "GameCount": "1",
        "Link": "Roison"
    },
    {
        "OverviewPage": "Route",
        "Champion": "Smolder",
        "TournamentLevel": "Primary",
        "GameCount": "2",
        "Link": "Route"
    },
    {
        "OverviewPage": "Ruep",
        "Champion": "Smolder",
        "TournamentLevel": "Secondary",
        "GameCount": "2",
        "Link": "Ruep"
    },
    {
        "OverviewPage": "Ruler",
        "Champion": "Smolder",
        "TournamentLevel": "Primary",
        "GameCount": "4",
        "Link": "Ruler"
    },
    {
        "OverviewPage": "Sajed",
        "Champion": "Smolder",
        "TournamentLevel": "Secondary",
        "GameCount": "3",
        "Link": "sajed"
    },
    {
        "OverviewPage": "Salami",
        "Champion": "Smolder",
        "TournamentLevel": "Secondary",
        "GameCount": "1",
        "Link": "Salami"
    },
    {
        "OverviewPage": "Sant",
        "Champion": "Smolder",
        "TournamentLevel": "Secondary",
        "GameCount": "1",
        "Link": "Sant"
    },
    {
        "OverviewPage": "Scarlet (Marcel Wiederhofer)",
        "Champion": "Smolder",
        "TournamentLevel": "Secondary",
        "GameCount": "2",
        "Link": "Scarlet (Marcel Wiederhofer)"
    },
    {
        "OverviewPage": "Scorth",
        "Champion": "Smolder",
        "TournamentLevel": "Secondary",
        "GameCount": "1",
        "Link": "Scorth"
    },
    {
        "OverviewPage": "Scuro",
        "Champion": "Smolder",
        "TournamentLevel": "Secondary",
        "GameCount": "1",
        "Link": "scuro"
    },
    {
        "OverviewPage": "Seelame",
        "Champion": "Smolder",
        "TournamentLevel": "Secondary",
        "GameCount": "1",
        "Link": "Seelame"
    },
    {
        "OverviewPage": "Serch",
        "Champion": "Smolder",
        "TournamentLevel": "Secondary",
        "GameCount": "3",
        "Link": "Serch"
    },
    {
        "OverviewPage": "Shaoye",
        "Champion": "Smolder",
        "TournamentLevel": "Primary",
        "GameCount": "2",
        "Link": "Shaoye"
    },
    {
        "OverviewPage": "Shir0",
        "Champion": "Smolder",
        "TournamentLevel": "Secondary",
        "GameCount": "1",
        "Link": "Shrio"
    },
    {
        "OverviewPage": "Shogun (Nguyễn Văn Huy)",
        "Champion": "Smolder",
        "TournamentLevel": "Primary",
        "GameCount": "5",
        "Link": "Shogun (Nguyễn Văn Huy)"
    },
    {
        "OverviewPage": "Shoto (Kylian Saadallah)",
        "Champion": "Smolder",
        "TournamentLevel": "Secondary",
        "GameCount": "2",
        "Link": "Shoto (Kylian Saadallah)"
    },
    {
        "OverviewPage": "SickN1ck",
        "Champion": "Smolder",
        "TournamentLevel": "Secondary",
        "GameCount": "3",
        "Link": "SickN1ck"
    },
    {
        "OverviewPage": "Sirinox",
        "Champion": "Smolder",
        "TournamentLevel": "Secondary",
        "GameCount": "2",
        "Link": "Sirinox"
    },
    {
        "OverviewPage": "SkaR",
        "Champion": "Smolder",
        "TournamentLevel": "Secondary",
        "GameCount": "1",
        "Link": "SkaR"
    },
    {
        "OverviewPage": "SkyeSunday",
        "Champion": "Smolder",
        "TournamentLevel": "Secondary",
        "GameCount": "1",
        "Link": "Skye Sunday"
    },
    {
        "OverviewPage": "Slayer (Kim Jin-young)",
        "Champion": "Smolder",
        "TournamentLevel": "Secondary",
        "GameCount": "7",
        "Link": "Slayer (Kim Jin-young)"
    },
    {
        "OverviewPage": "Slowz",
        "Champion": "Smolder",
        "TournamentLevel": "Primary",
        "GameCount": "2",
        "Link": "Slowz"
    },
    {
        "OverviewPage": "Smash (Sin Geum-jae)",
        "Champion": "Smolder",
        "TournamentLevel": "Secondary",
        "GameCount": "2",
        "Link": "Smash (Sin Geum-jae)"
    },
    {
        "OverviewPage": "SNAKER",
        "Champion": "Smolder",
        "TournamentLevel": "Primary",
        "GameCount": "1",
        "Link": "Snaker"
    },
    {
        "OverviewPage": "Sotsy",
        "Champion": "Smolder",
        "TournamentLevel": "Secondary",
        "GameCount": "1",
        "Link": "Sotsy"
    },
    {
        "OverviewPage": "Spawn (Trevor Kerr-Taylor)",
        "Champion": "Smolder",
        "TournamentLevel": "Secondary",
        "GameCount": "1",
        "Link": "Spawn (Trevor Kerr-Taylor)"
    },
    {
        "OverviewPage": "ST3PZ",
        "Champion": "Smolder",
        "TournamentLevel": "Secondary",
        "GameCount": "2",
        "Link": "ST3PZ"
    },
    {
        "OverviewPage": "Strode",
        "Champion": "Smolder",
        "TournamentLevel": "Secondary",
        "GameCount": "1",
        "Link": "Strode"
    },
    {
        "OverviewPage": "Sty1e",
        "Champion": "Smolder",
        "TournamentLevel": "Primary",
        "GameCount": "5",
        "Link": "Sty1e"
    },
    {
        "OverviewPage": "Subbex",
        "Champion": "Smolder",
        "TournamentLevel": "Secondary",
        "GameCount": "2",
        "Link": "Subbex"
    },
    {
        "OverviewPage": "Supa",
        "Champion": "Smolder",
        "TournamentLevel": "Primary",
        "GameCount": "1",
        "Link": "Supa"
    },
    {
        "OverviewPage": "Sushee",
        "Champion": "Smolder",
        "TournamentLevel": "Secondary",
        "GameCount": "1",
        "Link": "Sushee"
    },
    {
        "OverviewPage": "Syzyfek",
        "Champion": "Smolder",
        "TournamentLevel": "Secondary",
        "GameCount": "3",
        "Link": "Syzyfek"
    },
    {
        "OverviewPage": "T1en",
        "Champion": "Smolder",
        "TournamentLevel": "Secondary",
        "GameCount": "1",
        "Link": "T1en"
    },
    {
        "OverviewPage": "Taara",
        "Champion": "Smolder",
        "TournamentLevel": "Secondary",
        "GameCount": "2",
        "Link": "Taara"
    },
    {
        "OverviewPage": "Tactical",
        "Champion": "Smolder",
        "TournamentLevel": "Primary",
        "GameCount": "1",
        "Link": "Tactical"
    },
    {
        "OverviewPage": "Taeyoon",
        "Champion": "Smolder",
        "TournamentLevel": "Secondary",
        "GameCount": "4",
        "Link": "Taeyoon"
    },
    {
        "OverviewPage": "TakeSet",
        "Champion": "Smolder",
        "TournamentLevel": "Secondary",
        "GameCount": "1",
        "Link": "TakeSet"
    },
    {
        "OverviewPage": "Tazaku",
        "Champion": "Smolder",
        "TournamentLevel": "Secondary",
        "GameCount": "2",
        "Link": "Tazaku"
    },
    {
        "OverviewPage": "Teddy",
        "Champion": "Smolder",
        "TournamentLevel": "Primary",
        "GameCount": "4",
        "Link": "Teddy"
    },
    {
        "OverviewPage": "Theniz",
        "Champion": "Smolder",
        "TournamentLevel": "Secondary",
        "GameCount": "1",
        "Link": "Theniz"
    },
    {
        "OverviewPage": "Thesnake",
        "Champion": "Smolder",
        "TournamentLevel": "Primary",
        "GameCount": "2",
        "Link": "Thesnake"
    },
    {
        "OverviewPage": "Tide (Hsieh Yu-Che)",
        "Champion": "Smolder",
        "TournamentLevel": "Primary",
        "GameCount": "2",
        "Link": "Tide (Hsieh Yu-Che)"
    },
    {
        "OverviewPage": "TitaN",
        "Champion": "Smolder",
        "TournamentLevel": "Primary",
        "GameCount": "1",
        "Link": "TitaN"
    },
    {
        "OverviewPage": "Tomo",
        "Champion": "Smolder",
        "TournamentLevel": "Primary",
        "GameCount": "3",
        "Link": "Tomo"
    },
    {
        "OverviewPage": "Trigo (Matheus Trigo)",
        "Champion": "Smolder",
        "TournamentLevel": "Primary",
        "GameCount": "2",
        "Link": "Trigo (Matheus Trigo)"
    },
    {
        "OverviewPage": "TuokaZ",
        "Champion": "Smolder",
        "TournamentLevel": "Secondary",
        "GameCount": "2",
        "Link": "tuokaZ"
    },
    {
        "OverviewPage": "Vaynedeta",
        "Champion": "Smolder",
        "TournamentLevel": "Secondary",
        "GameCount": "1",
        "Link": "Vaynedeta"
    },
    {
        "OverviewPage": "Vertigo",
        "Champion": "Smolder",
        "TournamentLevel": "Secondary",
        "GameCount": "1",
        "Link": "Vertigo"
    },
    {
        "OverviewPage": "Vespa",
        "Champion": "Smolder",
        "TournamentLevel": "Secondary",
        "GameCount": "3",
        "Link": "Vespa"
    },
    {
        "OverviewPage": "Viper (Park Do-hyeon)",
        "Champion": "Smolder",
        "TournamentLevel": "Primary",
        "GameCount": "2",
        "Link": "Viper (Park Do-hyeon)"
    },
    {
        "OverviewPage": "Vital",
        "Champion": "Smolder",
        "TournamentLevel": "Secondary",
        "GameCount": "5",
        "Link": "vital"
    },
    {
        "OverviewPage": "WCD",
        "Champion": "Smolder",
        "TournamentLevel": "Secondary",
        "GameCount": "1",
        "Link": "WCD"
    },
    {
        "OverviewPage": "Whale",
        "Champion": "Smolder",
        "TournamentLevel": "Secondary",
        "GameCount": "5",
        "Link": "Whale"
    },
    {
        "OverviewPage": "Wixxi",
        "Champion": "Smolder",
        "TournamentLevel": "Secondary",
        "GameCount": "3",
        "Link": "Wixxi"
    },
    {
        "OverviewPage": "Woolite",
        "Champion": "Smolder",
        "TournamentLevel": "Secondary",
        "GameCount": "2",
        "Link": "Woolite"
    },
    {
        "OverviewPage": "Worst",
        "Champion": "Smolder",
        "TournamentLevel": "Secondary",
        "GameCount": "1",
        "Link": "Worst"
    },
    {
        "OverviewPage": "Xelar",
        "Champion": "Smolder",
        "TournamentLevel": "Secondary",
        "GameCount": "1",
        "Link": "Xelar"
    },
    {
        "OverviewPage": "Xeltop",
        "Champion": "Smolder",
        "TournamentLevel": "Secondary",
        "GameCount": "1",
        "Link": "Xeltop"
    },
    {
        "OverviewPage": "Xiaohanbao",
        "Champion": "Smolder",
        "TournamentLevel": "Secondary",
        "GameCount": "1",
        "Link": "xiaohanbao"
    },
    {
        "OverviewPage": "Xicor",
        "Champion": "Smolder",
        "TournamentLevel": "Secondary",
        "GameCount": "1",
        "Link": "Xicor"
    },
    {
        "OverviewPage": "Xingye",
        "Champion": "Smolder",
        "TournamentLevel": "Secondary",
        "GameCount": "1",
        "Link": "Xingye"
    },
    {
        "OverviewPage": "XLiang",
        "Champion": "Smolder",
        "TournamentLevel": "Secondary",
        "GameCount": "1",
        "Link": "xLiang"
    },
    {
        "OverviewPage": "XMatty",
        "Champion": "Smolder",
        "TournamentLevel": "Secondary",
        "GameCount": "2",
        "Link": "xMatty"
    },
    {
        "OverviewPage": "Yeon (Sean Sung)",
        "Champion": "Smolder",
        "TournamentLevel": "Primary",
        "GameCount": "2",
        "Link": "Yeon (Sean Sung)"
    },
    {
        "OverviewPage": "Yutapon",
        "Champion": "Smolder",
        "TournamentLevel": "Primary",
        "GameCount": "5",
        "Link": "Yutapon"
    },
    {
        "OverviewPage": "Z1n",
        "Champion": "Smolder",
        "TournamentLevel": "Secondary",
        "GameCount": "1",
        "Link": "z1n"
    },
    {
        "OverviewPage": "Zdz",
        "Champion": "Smolder",
        "TournamentLevel": "Primary",
        "GameCount": "1",
        "Link": "Zdz"
    },
    {
        "OverviewPage": "Zelvicka",
        "Champion": "Smolder",
        "TournamentLevel": "Secondary",
        "GameCount": "1",
        "Link": "Zelvicka"
    },
    {
        "OverviewPage": "Zhiqiuyi",
        "Champion": "Smolder",
        "TournamentLevel": "Secondary",
        "GameCount": "1",
        "Link": "zhiqiuyi"
    },
    {
        "OverviewPage": "Zka1",
        "Champion": "Smolder",
        "TournamentLevel": "Secondary",
        "GameCount": "1",
        "Link": "Zka1"
    },
    {
        "OverviewPage": "Zkaic",
        "Champion": "Smolder",
        "TournamentLevel": "Secondary",
        "GameCount": "4",
        "Link": "zkaic"
    },
    {
        "OverviewPage": "Zoiren",
        "Champion": "Smolder",
        "TournamentLevel": "Secondary",
        "GameCount": "2",
        "Link": "zoiren"
    }
]